practicusai/__init__.py
practicusaicore/__init__.py
practicusai-0.0.1.dist-info/METADATA
practicusai-0.0.1.dist-info/WHEEL
practicusai-0.0.1.dist-info/top_level.txt
practicusai-0.0.1.dist-info/RECORD
