Metadata-Version: 2.1
Name: practicusai
Version: 0.0.1
Summary: Please use practicus pypi package instead of this one..
Home-page: https://practicus.ai/
Author: Practicus AI
Author-email: info@practicus.ai
License: UNKNOWN
Platform: UNKNOWN
Requires-Python: >=3.10
